jay_ai/Dockerfile
jay_ai/License.txt
jay_ai/__init__.py
jay_ai/agent.py
jay_ai/agent_template.py
jay_ai/cli/init.py
jay_ai/cli_types.py
jay_ai/loader.py
jay_ai/main.py
jay_ai/plugins/azure.py
jay_ai/plugins/cartesia.py
jay_ai/plugins/deepgram.py
jay_ai/plugins/elevenlabs.py
jay_ai/plugins/fishaudio.py
jay_ai/plugins/google.py
jay_ai/plugins/openai.py
jay_ai/static/playground/404.html
jay_ai/static/playground/_next/static/chunks/39af6c14-c327a55a7e9e5b48.js
jay_ai/static/playground/_next/static/chunks/855-1473a9809f9c2d93.js
jay_ai/static/playground/_next/static/chunks/87c73c54-0a5376f9edecd876.js
jay_ai/static/playground/_next/static/chunks/963-75032b43882a5f55.js
jay_ai/static/playground/_next/static/chunks/app/_not-found/page-d020c160256d4457.js
jay_ai/static/playground/_next/static/chunks/app/layout-1593b0214383ce62.js
jay_ai/static/playground/_next/static/chunks/app/page-2fb1bddf6aa0f536.js
jay_ai/static/playground/_next/static/chunks/framework-ed3fb6b11445ee57.js
jay_ai/static/playground/_next/static/chunks/main-6a6deb4a2348cf9c.js
jay_ai/static/playground/_next/static/chunks/main-app-ac3bc5b8ddd12682.js
jay_ai/static/playground/_next/static/chunks/pages/_app-3e3e3e64529ea027.js
jay_ai/static/playground/_next/static/chunks/pages/_error-8cfbe37f68950a2b.js
jay_ai/static/playground/_next/static/chunks/polyfills-42372ed130431b0a.js
jay_ai/static/playground/_next/static/chunks/webpack-946e5c2f5b25da85.js
jay_ai/static/playground/_next/static/css/6271e0bb6a2798ba.css
jay_ai/static/playground/_next/static/hfcuR0B2JjlVkHJGg2Kf7/_buildManifest.js
jay_ai/static/playground/_next/static/hfcuR0B2JjlVkHJGg2Kf7/_ssgManifest.js
jay_ai/static/playground/_next/static/media/569ce4b8f30dc480-s.p.woff2
jay_ai/static/playground/_next/static/media/747892c23ea88013-s.woff2
jay_ai/static/playground/_next/static/media/93f479601ee12b01-s.p.woff2
jay_ai/static/playground/_next/static/media/ba015fad6dcf6784-s.woff2
jay_ai/static/playground/favicon.ico
jay_ai/static/playground/file.svg
jay_ai-0.8.0.dist-info/METADATA
jay_ai-0.8.0.dist-info/WHEEL
jay_ai-0.8.0.dist-info/entry_points.txt
jay_ai-0.8.0.dist-info/RECORD
